gladpy/__init__.py
gladpy/gladpy.py
gladpy-0.0.2.dist-info/LICENSE.txt
gladpy-0.0.2.dist-info/METADATA
gladpy-0.0.2.dist-info/WHEEL
gladpy-0.0.2.dist-info/top_level.txt
gladpy-0.0.2.dist-info/RECORD
