Metadata-Version: 2.1
Name: gladpy
Version: 0.0.2
Summary: GladPy is a small module in Python that is used to adding extensions for Python. It is also used for HTML as it generates HTML elements.
Home-page: https://github.com/kareemsaf/gladpy2
Author: kareemPypi
Author-email: s4830866@mkhg.moe.gov.sa
License: UNKNOWN
Project-URL: Bug Detector, https://github.com/kareemsaf/gladpy2/issues
Platform: UNKNOWN
Classifier: Programming Language :: Python :: 3
Classifier: License :: OSI Approved :: MIT License
Classifier: Operating System :: OS Independent
Requires-Python: >=3.8
License-File: LICENSE.txt
